shawn/__init__.py
shawn/__main__.py
shawn/build/__main__/Analysis-00.toc
shawn/build/__main__/PKG-00.pkg
shawn/build/__main__/PKG-00.toc
shawn/build/__main__/PYZ-00.pyz
shawn/build/__main__/PYZ-00.toc
shawn/build/__main__/base_library.zip
shawn/build/__main__/warn-__main__.txt
shawn/build/__main__/xref-__main__.html
shawn/cli.py
shawn/conftest.py
shawn/dist/__main__
shawn/gptassistant.py
shawn/utils.py
shawn-0.1.4.dist-info/LICENSE.md
shawn-0.1.4.dist-info/METADATA
shawn-0.1.4.dist-info/WHEEL
shawn-0.1.4.dist-info/entry_points.txt
shawn-0.1.4.dist-info/RECORD
