Metadata-Version: 2.1
Name: shawn
Version: 0.1.4
Summary: Use ChatGPT from terminal
Home-page: https://pypi.org/project/shawn
License: MIT
Author: William Bonvini
Author-email: william.bonvini@outlook.com
Requires-Python: >=3.8,<4.0
Classifier: Development Status :: 1 - Planning
Classifier: License :: OSI Approved :: MIT License
Classifier: Natural Language :: English
Classifier: Operating System :: OS Independent
Classifier: Programming Language :: Python
Classifier: Programming Language :: Python :: 3
Classifier: Programming Language :: Python :: 3.8
Classifier: Programming Language :: Python :: 3.9
Classifier: Programming Language :: Python :: 3.10
Classifier: Programming Language :: Python :: 3.11
Requires-Dist: halo (>=0.0.31,<0.0.32)
Requires-Dist: minilog
Requires-Dist: openai (>=0.27.6,<0.28.0)
Requires-Dist: rich (>=13.3.5,<14.0.0)
Requires-Dist: typer[all] (>=0.9.0,<0.10.0)
Project-URL: Documentation, https://shawn.readthedocs.io
Project-URL: Repository, https://github.com/WilliamBonvini/shawn
